{
  "kind": "collectionType",
  "collectionName": "embright_events",
  "info": {
    "name": "Embright Events"
  },
  "options": {
    "increments": true,
    "timestamps": true,
    "draftAndPublish": true
  },
  "pluginOptions": {},
  "attributes": {
    "Title": {
      "type": "string",
      "required": true
    },
    "Body": {
      "type": "richtext"
    },
    "coverImage": {
      "model": "file",
      "via": "related",
      "allowedTypes": [
        "images",
        "files",
        "videos"
      ],
      "plugin": "upload",
      "required": false,
      "pluginOptions": {}
    },
    "publishDate": {
      "type": "datetime"
    }
  }
}
